pyfido/__init__.py
pyfido/__main__.py
pyfido/client.py
pyfido-2.1.2.dist-info/LICENSE.txt
pyfido-2.1.2.dist-info/METADATA
pyfido-2.1.2.dist-info/WHEEL
pyfido-2.1.2.dist-info/entry_points.txt
pyfido-2.1.2.dist-info/top_level.txt
pyfido-2.1.2.dist-info/RECORD
