Metadata-Version: 2.1
Name: pyfido
Version: 2.1.2
Summary: Get your Fido consumption (wwww.fido.ca)
Home-page: http://github.com/titilambert/pyfido
Author: Thibault Cohen
Author-email: titilambert@gmail.com
License: Apache 2.0
Classifier: Programming Language :: Python :: 3.5
Classifier: Programming Language :: Python :: 3.6
Classifier: Programming Language :: Python :: 3.7
Classifier: Programming Language :: Python :: 3.8
Classifier: Programming Language :: Python :: 3.9
License-File: LICENSE.txt
